tabpfn_time_series/__init__.py
tabpfn_time_series/data_preparation.py
tabpfn_time_series/defaults.py
tabpfn_time_series/pipeline.py
tabpfn_time_series/plot.py
tabpfn_time_series/predictor.py
tabpfn_time_series/ts_dataframe.py
tabpfn_time_series/features/__init__.py
tabpfn_time_series/features/auto_features.py
tabpfn_time_series/features/basic_features.py
tabpfn_time_series/features/feature_generator_base.py
tabpfn_time_series/features/feature_transformer.py
tabpfn_time_series/worker/__init__.py
tabpfn_time_series/worker/model_adapters/__init__.py
tabpfn_time_series/worker/model_adapters/base.py
tabpfn_time_series/worker/model_adapters/tabpfn_adapter.py
tabpfn_time_series/worker/parallel_workers/__init__.py
tabpfn_time_series/worker/parallel_workers/base.py
tabpfn_time_series/worker/parallel_workers/cpu_worker.py
tabpfn_time_series/worker/parallel_workers/gpu_worker.py
tabpfn_time_series/worker/parallel_workers/tabpfn_client_worker.py
tabpfn_time_series-1.0.8.dist-info/METADATA
tabpfn_time_series-1.0.8.dist-info/WHEEL
tabpfn_time_series-1.0.8.dist-info/licenses/LICENSE.txt
tabpfn_time_series-1.0.8.dist-info/RECORD
