Metadata-Version: 2.4
Name: tabpfn_time_series
Version: 1.0.8
Summary: Zero-shot time series forecasting with TabPFNv2
Project-URL: Homepage, https://github.com/liam-sbhoo/tabpfn-time-series
Project-URL: Bug Tracker, https://github.com/liam-sbhoo/tabpfn-time-series/issues
Author-email: Liam Shi Bin Hoo <hoos@tf.uni-freiburg.de>
License-File: LICENSE.txt
Classifier: License :: OSI Approved :: Apache Software License
Classifier: Operating System :: OS Independent
Classifier: Programming Language :: Python :: 3
Requires-Python: >=3.10
Requires-Dist: autogluon-timeseries
Requires-Dist: backoff>=2.2.1
Requires-Dist: datasets>=2.15
Requires-Dist: fev>=0.6.1
Requires-Dist: gluonts>=0.16.0
Requires-Dist: pandas>=2.1.2
Requires-Dist: python-dotenv>=1.1.0
Requires-Dist: pyyaml>=6.0.1
Requires-Dist: statsmodels>=0.14.5
Requires-Dist: tabpfn-client>=0.1.7
Requires-Dist: tabpfn-common-utils[telemetry-interactive]>=0.2.2
Requires-Dist: tabpfn>=6.0.3
Requires-Dist: tqdm
